markdown_code_exec/__init__.py
markdown_code_exec/_app.py
markdown_code_exec/_markdown_code_exec.py
markdown_code_exec-0.3.0.dist-info/entry_points.txt
markdown_code_exec-0.3.0.dist-info/WHEEL
markdown_code_exec-0.3.0.dist-info/METADATA
markdown_code_exec-0.3.0.dist-info/RECORD
