Metadata-Version: 2.1
Name: markdown_code_exec
Version: 0.3.0
Summary: Executes Python code in Markdown files and captures the output
Author-email: Sebastiaan Mathot <s.mathot@cogsci.nl>
Requires-Python: >=3.5
Classifier: License :: OSI Approved :: GNU General Public License v3 or later (GPLv3+)
Project-URL: Documentation, https://github.com/smathot/markdown_code_exec
Project-URL: Source, https://github.com/smathot/markdown_code_exec
